pwgen2/__init__.py
pwgen2/__main__.py
pwgen2/__version__.py
pwgen2/cli/__init__.py
pwgen2/cli/__main__.py
pwgen2/cli/cli.py
pwgen2/pwgen2.py
pwgen2/showcase/__init__.py
pwgen2/showcase/__main__.py
pwgen2/showcase/pattern-list-error.txt
pwgen2/showcase/pattern-list.txt
pwgen2/showcase/showcase.py
task2b-1.0.19.dist-info/entry_points.txt
task2b-1.0.19.dist-info/LICENSE
task2b-1.0.19.dist-info/METADATA
task2b-1.0.19.dist-info/WHEEL
task2b-1.0.19.dist-info/RECORD
