Metadata-Version: 2.1
Name: task2b
Version: 1.0.19
Summary: Password generation CLI and library version 2
Home-page: https://gitlab.com/Bill-EPAM-DevOpsInt2023/python/task2b
License: MIT
Author: Bill.Avramenko
Author-email: billavramenko@gmail.com
Requires-Python: >=3.8,<4.0
Classifier: License :: OSI Approved :: MIT License
Classifier: Programming Language :: Python :: 3
Classifier: Programming Language :: Python :: 3.8
Classifier: Programming Language :: Python :: 3.9
Classifier: Programming Language :: Python :: 3.10
Classifier: Programming Language :: Python :: 3.11
Requires-Dist: questionary (>=1.10.0,<2.0.0)
Project-URL: Repository, https://gitlab.com/Bill-EPAM-DevOpsInt2023/python/task2b
